txt2voice/__init__.py
txt2voice/api.py
txt2voice/models.py
txt2voice-0.1.4.dist-info/LICENSE
txt2voice-0.1.4.dist-info/WHEEL
txt2voice-0.1.4.dist-info/METADATA
txt2voice-0.1.4.dist-info/RECORD
