Metadata-Version: 2.1
Name: txt2voice
Version: 0.1.4
Summary: Convert text to voice
Author: zemags
Requires-Python: >=3.9
Classifier: License :: OSI Approved :: MIT License
Classifier: Programming Language :: Python :: 3
Requires-Dist: pydub>=0.25.1
Requires-Dist: aiohttp>=3.8.1
Project-URL: Home, https://github.com/zemags/python-yandex-speech-kit
